naxai/__init__.py
naxai/async_client.py
naxai/client.py
naxai/config.py
naxai/base/__init__.py
naxai/base/base_client.py
naxai/base/exceptions.py
naxai/models/__init__.py
naxai/models/token_response.py
naxai/models/base/__init__.py
naxai/models/base/pagination.py
naxai/models/calendars/__init__.py
naxai/models/calendars/calendar.py
naxai/models/calendars/schedule_object.py
naxai/models/calendars/requests/__init__.py
naxai/models/calendars/requests/calendar_requests.py
naxai/models/calendars/responses/__init__.py
naxai/models/calendars/responses/calendars_responses.py
naxai/models/calendars/responses/holidays_template_responses.py
naxai/models/email/__init__.py
naxai/models/email/requests/__init__.py
naxai/models/email/requests/transactional_requests.py
naxai/models/email/responses/__init__.py
naxai/models/email/responses/activity_logs_responses.py
naxai/models/email/responses/metrics_responses.py
naxai/models/email/responses/transactional_responses.py
naxai/models/people/__init__.py
naxai/models/people/helper_models/__init__.py
naxai/models/people/helper_models/search_condition.py
naxai/models/people/helper_models/segments_condition.py
naxai/models/people/requests/__init__.py
naxai/models/people/requests/segments_requests.py
naxai/models/people/responses/__init__.py
naxai/models/people/responses/attributes_responses.py
naxai/models/people/responses/contacts_responses.py
naxai/models/people/responses/segments_responses.py
naxai/models/sms/__init__.py
naxai/models/sms/responses/__init__.py
naxai/models/sms/responses/activity_logs_responses.py
naxai/models/sms/responses/reporting_responses.py
naxai/models/sms/responses/send_responses.py
naxai/models/voice/__init__.py
naxai/models/voice/voice_flow.py
naxai/models/voice/requests/__init__.py
naxai/models/voice/requests/broadcasts_requests.py
naxai/models/voice/requests/call_requests.py
naxai/models/voice/responses/__init__.py
naxai/models/voice/responses/activity_logs_responses.py
naxai-0.0.49.dist-info/METADATA
naxai-0.0.49.dist-info/WHEEL
naxai-0.0.49.dist-info/top_level.txt
naxai-0.0.49.dist-info/RECORD
