Metadata-Version: 2.4
Name: naxai
Version: 0.0.49
Summary: Python sdk for Naxai's API
Home-page: https://github.com/kevinRR2018/naxai-sdk-python
Author: kevin
Author-email: k.bertin@ringring.be
Keywords: voice,naxai,sdk,sms,email,communication
Requires-Dist: pydantic>=2.0
Requires-Dist: httpx
Dynamic: author
Dynamic: author-email
Dynamic: home-page
Dynamic: keywords
Dynamic: requires-dist
Dynamic: summary
